ncbi_taxon_db/__init__.py
ncbi_taxon_db/child_nodes.marisa
ncbi_taxon_db/child_nodes.zstd
ncbi_taxon_db/common_name.marisa
ncbi_taxon_db/common_name.zstd
ncbi_taxon_db/description.marisa
ncbi_taxon_db/description.zstd
ncbi_taxon_db/en_wiki_title.marisa
ncbi_taxon_db/en_wiki_title.zstd
ncbi_taxon_db/host.marisa
ncbi_taxon_db/host.zstd
ncbi_taxon_db/scientific_name.marisa
ncbi_taxon_db/scientific_name.zstd
ncbi_taxon_db/sn2taxid.marisa
ncbi_taxon_db/taxa.marisa
ncbi_taxon_db/taxid2refrep.marisa
ncbi_taxon_db/taxid2refrep.zstd
ncbi_taxon_db/taxid2refseq.marisa
ncbi_taxon_db/taxid2refseq.zstd
ncbi_taxon_db/version.py
ncbi_taxon_db/wikidata.marisa
ncbi_taxon_db-2024.9.7.dist-info/METADATA
ncbi_taxon_db-2024.9.7.dist-info/WHEEL
ncbi_taxon_db-2024.9.7.dist-info/top_level.txt
ncbi_taxon_db-2024.9.7.dist-info/RECORD
