Metadata-Version: 2.1
Name: ncbi-taxon-db
Version: 2024.9.7
Summary: Taxoniq index for NCBI Taxonomy database
Home-page: https://github.com/chanzuckerberg/taxoniq
Author: Andrey Kislyuk
Author-email: akislyuk@chanzuckerberg.com
License: MIT License
Requires-Dist: ncbi-refseq-accession-db==2024.9.07
Requires-Dist: ncbi-refseq-accession-lengths==2024.9.07
Requires-Dist: ncbi-refseq-accession-offsets==2024.9.07
